pysen_plugins/__init__.py
pysen_plugins/_version.py
pysen_plugins/clang_format.py
pysen_plugins/cmake_format.py
pysen_plugins/golint.py
pysen_plugins/goreturns.py
pysen_plugins/jq.py
pysen_plugins/mypy_init_check.py
pysen_plugins/mypy_simple.py
pysen_plugins/prettier.py
pysen_plugins/py.typed
pysen_plugins/ruamel_yaml.py
pysen_plugins/shellcheck.py
pysen_plugins/shfmt.py
pysen_plugins/tidy.py
pysen_plugins/customizable_builtins/__init__.py
pysen_plugins/customizable_builtins/black.py
pysen_plugins/customizable_builtins/flake8.py
pysen_plugins/customizable_builtins/isort.py
pysen_plugins/customizable_builtins/mypy.py
pysen_plugins/customizable_builtins/plugin.py
pysen_plugins/pylint/__init__.py
pysen_plugins/pylint/command.py
pysen_plugins/pylint/component.py
pysen_plugins/pylint/plugin.py
pysen_plugins/ruff/__init__.py
pysen_plugins/ruff/plugin.py
pysen_plugins/ruff/preset.py
pysen_plugins-2024.7.17.dist-info/LICENSE
pysen_plugins-2024.7.17.dist-info/METADATA
pysen_plugins-2024.7.17.dist-info/WHEEL
pysen_plugins-2024.7.17.dist-info/top_level.txt
pysen_plugins-2024.7.17.dist-info/RECORD
