Metadata-Version: 2.1
Name: pysen-plugins
Version: 2024.7.17
Summary: Collection of pysen plugins
Author: Toru Ogawa, Ryo Miyajima, Linsho Kaku
Author-email: ogawa@preferred.jp, ryo@preferred.jp, linsho@preferred.jp
License: MIT License
Classifier: Programming Language :: Python :: 3.8
Classifier: Programming Language :: Python :: 3.9
Classifier: Programming Language :: Python :: 3.10
Classifier: Programming Language :: Python :: 3.11
Classifier: Programming Language :: Python :: 3.12
Classifier: Programming Language :: Python
Classifier: License :: OSI Approved :: MIT License
Classifier: Operating System :: POSIX
Classifier: Operating System :: MacOS
Classifier: Operating System :: Unix
License-File: LICENSE
Requires-Dist: pysen <0.12.0,>=0.11.0
